{
  "match_id": 46,
  "event_id": "760450",
  "teams": {
    "Uruguay": {
      "foulsCommitted": 11.0,
      "yellowCards": 2.0,
      "redCards": 0.0,
      "offsides": 3.0,
      "wonCorners": 11.0,
      "saves": 2.0,
      "possessionPct": 65.2,
      "totalShots": 17.0,
      "shotsOnTarget": 2.0,
      "shotPct": 0.1,
      "penaltyKickGoals": 0.0,
      "penaltyKickShots": 0.0,
      "accuratePasses": 420.0,
      "totalPasses": 511.0,
      "passPct": 0.8,
      "accurateCrosses": 4.0,
      "totalCrosses": 29.0,
      "crossPct": 0.1,
      "totalLongBalls": 48.0,
      "accurateLongBalls": 23.0,
      "longballPct": 0.5,
      "blockedShots": 7.0,
      "effectiveTackles": 8.0,
      "totalTackles": 16.0,
      "tacklePct": 0.5,
      "interceptions": 7.0,
      "effectiveClearance": 11.0,
      "totalClearance": 11.0
    },
    "Cape Verde": {
      "foulsCommitted": 4.0,
      "yellowCards": 2.0,
      "redCards": 0.0,
      "offsides": 0.0,
      "wonCorners": 4.0,
      "saves": 0.0,
      "possessionPct": 34.8,
      "totalShots": 12.0,
      "shotsOnTarget": 4.0,
      "shotPct": 0.3,
      "penaltyKickGoals": 0.0,
      "penaltyKickShots": 0.0,
      "accuratePasses": 205.0,
      "totalPasses": 278.0,
      "passPct": 0.7,
      "accurateCrosses": 2.0,
      "totalCrosses": 7.0,
      "crossPct": 0.3,
      "totalLongBalls": 61.0,
      "accurateLongBalls": 18.0,
      "longballPct": 0.3,
      "blockedShots": 4.0,
      "effectiveTackles": 15.0,
      "totalTackles": 16.0,
      "tacklePct": 0.9,
      "interceptions": 13.0,
      "effectiveClearance": 48.0,
      "totalClearance": 48.0
    }
  },
  "players": {
    "Uruguay": [
      {
        "name": "Fernando Muslera",
        "position": "G",
        "starter": true,
        "jersey": "23",
        "stats": {
          "appearances": "1",
          "foulsCommitted": "0",
          "foulsSuffered": "0",
          "ownGoals": "0",
          "redCards": "0",
          "subIns": "0",
          "yellowCards": "0",
          "goalsConceded": "2",
          "saves": "2",
          "shotsFaced": "0",
          "goalAssists": "0",
          "shotsOnTarget": "0",
          "totalGoals": "0",
          "totalShots": "0"
        }
      },
      {
        "name": "Mathías Olivera",
        "position": "CD-L",
        "starter": true,
        "jersey": "16",
        "stats": {
          "appearances": "1",
          "foulsCommitted": "1",
          "foulsSuffered": "0",
          "ownGoals": "0",
          "redCards": "0",
          "subIns": "0",
          "yellowCards": "1",
          "goalsConceded": "2",
          "shotsFaced": "0",
          "goalAssists": "0",
          "offsides": "0",
          "shotsOnTarget": "0",
          "totalGoals": "0",
          "totalShots": "0"
        }
      },
      {
        "name": "Sebastián Cáceres",
        "position": "CD-R",
        "starter": true,
        "jersey": "3",
        "stats": {
          "appearances": "1",
          "foulsCommitted": "1",
          "foulsSuffered": "0",
          "ownGoals": "0",
          "redCards": "0",
          "subIns": "0",
          "yellowCards": "0",
          "goalsConceded": "2",
          "shotsFaced": "0",
          "goalAssists": "0",
          "offsides": "0",
          "shotsOnTarget": "0",
          "totalGoals": "0",
          "totalShots": "1"
        }
      },
      {
        "name": "Manuel Ugarte",
        "position": "DM",
        "starter": true,
        "jersey": "5",
        "stats": {
          "appearances": "1",
          "foulsCommitted": "1",
          "foulsSuffered": "0",
          "ownGoals": "0",
          "redCards": "0",
          "subIns": "0",
          "yellowCards": "0",
          "goalsConceded": "2",
          "shotsFaced": "0",
          "goalAssists": "0",
          "offsides": "0",
          "shotsOnTarget": "0",
          "totalGoals": "0",
          "totalShots": "1"
        }
      },
      {
        "name": "Juan Manuel Sanabria",
        "position": "LB",
        "starter": true,
        "jersey": "25",
        "stats": {
          "appearances": "1",
          "foulsCommitted": "0",
          "foulsSuffered": "0",
          "ownGoals": "0",
          "redCards": "0",
          "subIns": "0",
          "yellowCards": "0",
          "goalsConceded": "2",
          "shotsFaced": "0",
          "goalAssists": "0",
          "offsides": "0",
          "shotsOnTarget": "0",
          "totalGoals": "0",
          "totalShots": "0"
        }
      },
      {
        "name": "Guillermo Varela",
        "position": "RB",
        "starter": true,
        "jersey": "13",
        "stats": {
          "appearances": "1",
          "foulsCommitted": "0",
          "foulsSuffered": "0",
          "ownGoals": "0",
          "redCards": "0",
          "subIns": "0",
          "yellowCards": "0",
          "goalsConceded": "2",
          "shotsFaced": "0",
          "goalAssists": "0",
          "offsides": "0",
          "shotsOnTarget": "0",
          "totalGoals": "0",
          "totalShots": "0"
        }
      },
      {
        "name": "Federico Valverde",
        "position": "CM-L",
        "starter": true,
        "jersey": "8",
        "stats": {
          "appearances": "1",
          "foulsCommitted": "0",
          "foulsSuffered": "0",
          "ownGoals": "0",
          "redCards": "0",
          "subIns": "0",
          "yellowCards": "0",
          "goalsConceded": "2",
          "shotsFaced": "0",
          "goalAssists": "0",
          "offsides": "0",
          "shotsOnTarget": "0",
          "totalGoals": "0",
          "totalShots": "7"
        }
      },
      {
        "name": "Rodrigo Bentancur",
        "position": "CM-R",
        "starter": true,
        "jersey": "6",
        "stats": {
          "appearances": "1",
          "foulsCommitted": "3",
          "foulsSuffered": "1",
          "ownGoals": "0",
          "redCards": "0",
          "subIns": "0",
          "yellowCards": "1",
          "goalsConceded": "2",
          "shotsFaced": "0",
          "goalAssists": "0",
          "offsides": "0",
          "shotsOnTarget": "0",
          "totalGoals": "0",
          "totalShots": "2"
        }
      },
      {
        "name": "Maxi Araújo",
        "position": "LM",
        "starter": true,
        "jersey": "20",
        "stats": {
          "appearances": "1",
          "foulsCommitted": "1",
          "foulsSuffered": "1",
          "ownGoals": "0",
          "redCards": "0",
          "subIns": "0",
          "yellowCards": "0",
          "goalsConceded": "2",
          "shotsFaced": "0",
          "goalAssists": "1",
          "offsides": "2",
          "shotsOnTarget": "1",
          "totalGoals": "1",
          "totalShots": "2"
        }
      },
      {
        "name": "Agustín Canobbio",
        "position": "RM",
        "starter": true,
        "jersey": "14",
        "stats": {
          "appearances": "1",
          "foulsCommitted": "4",
          "foulsSuffered": "0",
          "ownGoals": "0",
          "redCards": "0",
          "subIns": "0",
          "yellowCards": "0",
          "goalsConceded": "2",
          "shotsFaced": "0",
          "goalAssists": "0",
          "offsides": "0",
          "shotsOnTarget": "1",
          "totalGoals": "1",
          "totalShots": "2"
        }
      },
      {
        "name": "Federico Viñas",
        "position": "F",
        "starter": true,
        "jersey": "21",
        "stats": {
          "appearances": "1",
          "foulsCommitted": "0",
          "foulsSuffered": "1",
          "ownGoals": "0",
          "redCards": "0",
          "subIns": "0",
          "yellowCards": "0",
          "goalsConceded": "2",
          "shotsFaced": "0",
          "goalAssists": "0",
          "offsides": "1",
          "shotsOnTarget": "0",
          "totalGoals": "0",
          "totalShots": "0"
        }
      },
      {
        "name": "Nicolás de la Cruz",
        "position": "SUB",
        "starter": false,
        "jersey": "7",
        "stats": {
          "appearances": "1",
          "foulsCommitted": "0",
          "foulsSuffered": "1",
          "ownGoals": "0",
          "redCards": "0",
          "subIns": "1",
          "yellowCards": "0",
          "goalsConceded": "0",
          "shotsFaced": "0",
          "goalAssists": "0",
          "offsides": "0",
          "shotsOnTarget": "0",
          "totalGoals": "0",
          "totalShots": "1"
        }
      },
      {
        "name": "Brian Rodríguez",
        "position": "SUB",
        "starter": false,
        "jersey": "18",
        "stats": {
          "appearances": "1",
          "foulsCommitted": "0",
          "foulsSuffered": "0",
          "ownGoals": "0",
          "redCards": "0",
          "subIns": "1",
          "yellowCards": "0",
          "goalsConceded": "0",
          "shotsFaced": "0",
          "goalAssists": "0",
          "offsides": "0",
          "shotsOnTarget": "0",
          "totalGoals": "0",
          "totalShots": "1"
        }
      },
      {
        "name": "Darwin Núñez",
        "position": "SUB",
        "starter": false,
        "jersey": "9",
        "stats": {
          "appearances": "1",
          "foulsCommitted": "0",
          "foulsSuffered": "0",
          "ownGoals": "0",
          "redCards": "0",
          "subIns": "1",
          "yellowCards": "0",
          "goalsConceded": "0",
          "shotsFaced": "0",
          "goalAssists": "0",
          "offsides": "0",
          "shotsOnTarget": "0",
          "totalGoals": "0",
          "totalShots": "0"
        }
      }
    ],
    "Cape Verde": [
      {
        "name": "Vozinha",
        "position": "G",
        "starter": true,
        "jersey": "1",
        "stats": {
          "appearances": "1",
          "foulsCommitted": "0",
          "foulsSuffered": "0",
          "ownGoals": "0",
          "redCards": "0",
          "subIns": "0",
          "yellowCards": "0",
          "goalsConceded": "2",
          "saves": "0",
          "shotsFaced": "0",
          "goalAssists": "0",
          "shotsOnTarget": "0",
          "totalGoals": "0",
          "totalShots": "0"
        }
      },
      {
        "name": "Diney Borges",
        "position": "CD-L",
        "starter": true,
        "jersey": "3",
        "stats": {
          "appearances": "1",
          "foulsCommitted": "0",
          "foulsSuffered": "0",
          "ownGoals": "0",
          "redCards": "0",
          "subIns": "0",
          "yellowCards": "1",
          "goalsConceded": "2",
          "shotsFaced": "0",
          "goalAssists": "0",
          "offsides": "0",
          "shotsOnTarget": "0",
          "totalGoals": "0",
          "totalShots": "1"
        }
      },
      {
        "name": "Pico Lopes",
        "position": "CD-R",
        "starter": true,
        "jersey": "4",
        "stats": {
          "appearances": "1",
          "foulsCommitted": "0",
          "foulsSuffered": "0",
          "ownGoals": "0",
          "redCards": "0",
          "subIns": "0",
          "yellowCards": "0",
          "goalsConceded": "2",
          "shotsFaced": "0",
          "goalAssists": "0",
          "offsides": "0",
          "shotsOnTarget": "0",
          "totalGoals": "0",
          "totalShots": "1"
        }
      },
      {
        "name": "Kevin Pina",
        "position": "DM",
        "starter": true,
        "jersey": "6",
        "stats": {
          "appearances": "1",
          "foulsCommitted": "1",
          "foulsSuffered": "0",
          "ownGoals": "0",
          "redCards": "0",
          "subIns": "0",
          "yellowCards": "0",
          "goalsConceded": "2",
          "shotsFaced": "0",
          "goalAssists": "0",
          "offsides": "0",
          "shotsOnTarget": "1",
          "totalGoals": "1",
          "totalShots": "1"
        }
      },
      {
        "name": "Sidny Lopes Cabral",
        "position": "LB",
        "starter": true,
        "jersey": "13",
        "stats": {
          "appearances": "1",
          "foulsCommitted": "1",
          "foulsSuffered": "5",
          "ownGoals": "0",
          "redCards": "0",
          "subIns": "0",
          "yellowCards": "1",
          "goalsConceded": "2",
          "shotsFaced": "0",
          "goalAssists": "0",
          "offsides": "0",
          "shotsOnTarget": "0",
          "totalGoals": "0",
          "totalShots": "2"
        }
      },
      {
        "name": "Steven Moreira",
        "position": "RB",
        "starter": true,
        "jersey": "22",
        "stats": {
          "appearances": "1",
          "foulsCommitted": "0",
          "foulsSuffered": "0",
          "ownGoals": "0",
          "redCards": "0",
          "subIns": "0",
          "yellowCards": "0",
          "goalsConceded": "2",
          "shotsFaced": "0",
          "goalAssists": "0",
          "offsides": "0",
          "shotsOnTarget": "0",
          "totalGoals": "0",
          "totalShots": "0"
        }
      },
      {
        "name": "Jamiro Monteiro",
        "position": "CM-L",
        "starter": true,
        "jersey": "10",
        "stats": {
          "appearances": "1",
          "foulsCommitted": "0",
          "foulsSuffered": "1",
          "ownGoals": "0",
          "redCards": "0",
          "subIns": "0",
          "yellowCards": "0",
          "goalsConceded": "2",
          "shotsFaced": "0",
          "goalAssists": "0",
          "offsides": "0",
          "shotsOnTarget": "0",
          "totalGoals": "0",
          "totalShots": "2"
        }
      },
      {
        "name": "Telmo Arcanjo",
        "position": "CM-R",
        "starter": true,
        "jersey": "18",
        "stats": {
          "appearances": "1",
          "foulsCommitted": "0",
          "foulsSuffered": "1",
          "ownGoals": "0",
          "redCards": "0",
          "subIns": "0",
          "yellowCards": "0",
          "goalsConceded": "2",
          "shotsFaced": "0",
          "goalAssists": "0",
          "offsides": "0",
          "shotsOnTarget": "0",
          "totalGoals": "0",
          "totalShots": "0"
        }
      },
      {
        "name": "Garry Rodrigues",
        "position": "LM",
        "starter": true,
        "jersey": "11",
        "stats": {
          "appearances": "1",
          "foulsCommitted": "0",
          "foulsSuffered": "0",
          "ownGoals": "0",
          "redCards": "0",
          "subIns": "0",
          "yellowCards": "0",
          "goalsConceded": "2",
          "shotsFaced": "0",
          "goalAssists": "0",
          "offsides": "0",
          "shotsOnTarget": "0",
          "totalGoals": "0",
          "totalShots": "0"
        }
      },
      {
        "name": "Ryan Mendes",
        "position": "RM",
        "starter": true,
        "jersey": "20",
        "stats": {
          "appearances": "1",
          "foulsCommitted": "0",
          "foulsSuffered": "0",
          "ownGoals": "0",
          "redCards": "0",
          "subIns": "0",
          "yellowCards": "0",
          "goalsConceded": "2",
          "shotsFaced": "0",
          "goalAssists": "0",
          "offsides": "0",
          "shotsOnTarget": "0",
          "totalGoals": "0",
          "totalShots": "2"
        }
      },
      {
        "name": "Gilson Benchimol",
        "position": "F",
        "starter": true,
        "jersey": "9",
        "stats": {
          "appearances": "1",
          "foulsCommitted": "0",
          "foulsSuffered": "1",
          "ownGoals": "0",
          "redCards": "0",
          "subIns": "0",
          "yellowCards": "0",
          "goalsConceded": "2",
          "shotsFaced": "0",
          "goalAssists": "0",
          "offsides": "0",
          "shotsOnTarget": "0",
          "totalGoals": "0",
          "totalShots": "0"
        }
      },
      {
        "name": "Deroy Duarte",
        "position": "SUB",
        "starter": false,
        "jersey": "14",
        "stats": {
          "appearances": "1",
          "foulsCommitted": "1",
          "foulsSuffered": "0",
          "ownGoals": "0",
          "redCards": "0",
          "subIns": "1",
          "yellowCards": "0",
          "goalsConceded": "0",
          "shotsFaced": "0",
          "goalAssists": "0",
          "offsides": "0",
          "shotsOnTarget": "0",
          "totalGoals": "0",
          "totalShots": "0"
        }
      },
      {
        "name": "Yannick Semedo",
        "position": "SUB",
        "starter": false,
        "jersey": "16",
        "stats": {
          "appearances": "1",
          "foulsCommitted": "1",
          "foulsSuffered": "1",
          "ownGoals": "0",
          "redCards": "0",
          "subIns": "1",
          "yellowCards": "0",
          "goalsConceded": "0",
          "shotsFaced": "0",
          "goalAssists": "0",
          "offsides": "0",
          "shotsOnTarget": "0",
          "totalGoals": "0",
          "totalShots": "0"
        }
      },
      {
        "name": "Nuno da Costa",
        "position": "SUB",
        "starter": false,
        "jersey": "21",
        "stats": {
          "appearances": "1",
          "foulsCommitted": "0",
          "foulsSuffered": "1",
          "ownGoals": "0",
          "redCards": "0",
          "subIns": "1",
          "yellowCards": "0",
          "goalsConceded": "0",
          "shotsFaced": "0",
          "goalAssists": "0",
          "offsides": "0",
          "shotsOnTarget": "0",
          "totalGoals": "0",
          "totalShots": "0"
        }
      },
      {
        "name": "Laros Duarte",
        "position": "SUB",
        "starter": false,
        "jersey": "15",
        "stats": {
          "appearances": "1",
          "foulsCommitted": "0",
          "foulsSuffered": "1",
          "ownGoals": "0",
          "redCards": "0",
          "subIns": "1",
          "yellowCards": "0",
          "goalsConceded": "0",
          "shotsFaced": "0",
          "goalAssists": "0",
          "offsides": "0",
          "shotsOnTarget": "2",
          "totalGoals": "0",
          "totalShots": "2"
        }
      },
      {
        "name": "Hélio Varela",
        "position": "SUB",
        "starter": false,
        "jersey": "26",
        "stats": {
          "appearances": "1",
          "foulsCommitted": "0",
          "foulsSuffered": "0",
          "ownGoals": "0",
          "redCards": "0",
          "subIns": "1",
          "yellowCards": "0",
          "goalsConceded": "0",
          "shotsFaced": "0",
          "goalAssists": "0",
          "offsides": "0",
          "shotsOnTarget": "1",
          "totalGoals": "1",
          "totalShots": "1"
        }
      }
    ]
  },
  "officials": [
    {
      "name": "Espen Eskas",
      "role": "Referee"
    }
  ]
}